robotestrail/__init__.py
robotestrail/config_manager.py
robotestrail/csv_generator.py
robotestrail/handlers.py
robotestrail/logging_config.py
robotestrail/main.py
robotestrail/robot_framework_utils.py
robotestrail/test_sync_manager.py
robotestrail/testrail_api_manager.py
robotframework_testrail_sync-0.0.31.dist-info/LICENSE
robotframework_testrail_sync-0.0.31.dist-info/METADATA
robotframework_testrail_sync-0.0.31.dist-info/WHEEL
robotframework_testrail_sync-0.0.31.dist-info/entry_points.txt
robotframework_testrail_sync-0.0.31.dist-info/top_level.txt
robotframework_testrail_sync-0.0.31.dist-info/RECORD
